certificate_watcher.py
certificate_watcher-0.2.0.dist-info/METADATA
certificate_watcher-0.2.0.dist-info/WHEEL
certificate_watcher-0.2.0.dist-info/entry_points.txt
certificate_watcher-0.2.0.dist-info/top_level.txt
certificate_watcher-0.2.0.dist-info/RECORD
