Metadata-Version: 2.1
Name: certificate_watcher
Version: 0.2.0
Summary: Watch expiration of certificates of a bunch of websites.
Author-email: Julien Palard <julien@palard.fr>
License: MIT license
Project-URL: homepage, https://github.com/JulienPalard/certificate_watcher
Keywords: ssl,tls,certificate,https,watch,sysadmin,cron,ocsp
Classifier: Development Status :: 4 - Beta
Classifier: Intended Audience :: System Administrators
Classifier: License :: OSI Approved :: MIT License
Classifier: Natural Language :: English
Classifier: Programming Language :: Python :: 3
Requires-Python: >=3.7
Requires-Dist: ocsp-checker
